code_runner_sdk/__init__.py
code_runner_sdk/core/client.py
code_runner_sdk/core/config.py
code_runner_sdk/examples/basic_usage.py
code_runner_sdk/exceptions/__init__.py
code_runner_sdk/http/client.py
code_runner_sdk/models/code_execution.py
code_runner_sdk-0.1.1.dist-info/METADATA
code_runner_sdk-0.1.1.dist-info/WHEEL
code_runner_sdk-0.1.1.dist-info/top_level.txt
code_runner_sdk-0.1.1.dist-info/RECORD
