Metadata-Version: 2.1
Name: code-runner-sdk
Version: 0.1.1
Summary: Code Runner Sandbox服务的Python SDK
Home-page: https://github.com/shouldnotappearcalm/Code-Runner-Sandbox
Author: calm
Author-email: losergzr@gmail.com
License: UNKNOWN
Platform: UNKNOWN
Classifier: Development Status :: 3 - Alpha
Classifier: Intended Audience :: Developers
Classifier: License :: OSI Approved :: MIT License
Classifier: Operating System :: OS Independent
Classifier: Programming Language :: Python :: 3
Classifier: Programming Language :: Python :: 3.7
Classifier: Programming Language :: Python :: 3.8
Classifier: Programming Language :: Python :: 3.9
Classifier: Programming Language :: Python :: 3.10
Requires-Python: >=3.7
Requires-Dist: requests (>=2.25.0)
Requires-Dist: pydantic (>=1.8.0)
